dollop/__init__.py
dollop/auto.py
dollop/file.py
dollop/numpy.py
dollop/pandas.py
dollop/sequence.py
dollop/torch.py
dollop-1.1.0.dist-info/licenses/LICENSE
dollop-1.1.0.dist-info/METADATA
dollop-1.1.0.dist-info/WHEEL
dollop-1.1.0.dist-info/top_level.txt
dollop-1.1.0.dist-info/RECORD
