Metadata-Version: 2.4
Name: dollop
Version: 1.1.0
Author: Michael Peter Dunne
Classifier: Programming Language :: Python :: 3
Classifier: License :: OSI Approved :: MIT License
Requires-Python: >=3.8
License-File: LICENSE
Dynamic: license-file
